MANIFEST.in
README.md
setup.py
cart/__init__.py
cart/forms.py
cart/middleware.py
cart/service.py
cart/urls.py
cart/views.py
cart/locale/ru/LC_MESSAGES/django.mo
cart/locale/ru/LC_MESSAGES/django.po
cart/locale/uk/LC_MESSAGES/django.mo
cart/locale/uk/LC_MESSAGES/django.po
cart/static/css/cart.css
cart/static/js/cart.js
cart/templates/cart-modal.html
django_mp_cart.egg-info/PKG-INFO
django_mp_cart.egg-info/SOURCES.txt
django_mp_cart.egg-info/dependency_links.txt
django_mp_cart.egg-info/top_level.txt