Metadata-Version: 2.1
Name: django-mp-cart
Version: 2.0.6
Summary: Django cart app
Home-page: https://github.com/pmaigutyak/mp-cart
Download-URL: https://github.com/pmaigutyak/mp-cart/archive/2.0.6.tar.gz
Author: Paul Maigutyak
Author-email: pmaigutyak@gmail.com
License: MIT
